mkfol/__init__.py
mkfol/ds2.py
mkfol/ds_ml.py
mkfol/mkfol.py
mkfol/semester.py
mkfol/semester_week.py
mkfol-1.1.4.dist-info/METADATA
mkfol-1.1.4.dist-info/WHEEL
mkfol-1.1.4.dist-info/entry_points.txt
mkfol-1.1.4.dist-info/top_level.txt
mkfol-1.1.4.dist-info/RECORD
